{"records": [{"url": "http://angelist.co.kr/505", "timestamp": 1380372837.0, "vendor": "Angel`s Private Space", "id": "http://angelist.co.kr/505", "title": "환영을 달리는 태양 13화[完] 자막"}, {"url": "http://angelist.co.kr/504", "timestamp": 1380320354.0, "vendor": "Angel`s Private Space", "id": "http://angelist.co.kr/504", "title": "일본 여행 3일 차 (2013.01.17) - 02. 시오미, 호텔 체크인"}, {"url": "http://angelist.co.kr/503", "timestamp": 1379804314.0, "vendor": "Angel`s Private Space", "id": "http://angelist.co.kr/503", "title": "환영을 달리는 태양 12화 자막"}, {"url": "http://angelist.co.kr/502", "timestamp": 1379199787.0, "vendor": "Angel`s Private Space", "id": "http://angelist.co.kr/502", "title": "환영을 달리는 태양 11화 자막"}, {"url": "http://angelist.co.kr/501", "timestamp": 1378573132.0, "vendor": "Angel`s Private Space", "id": "http://angelist.co.kr/501", "title": "환영을 달리는 태양 10화 자막"}, {"url": "http://angelist.co.kr/500", "timestamp": 1378000918.0, "vendor": "Angel`s Private Space", "id": "http://angelist.co.kr/500", "title": "포토카노 BD 제2권 자막"}, {"url": "http://angelist.co.kr/499", "timestamp": 1377962379.0, "vendor": "Angel`s Private Space", "id": "http://angelist.co.kr/499", "title": "환영을 달리는 태양 9화 자막"}, {"url": "http://fuko.tistory.com/1137", "timestamp": 1380266971, "vendor": "Stankovic", "id": "http://fuko.tistory.com/1137", "title": "어떤 과학의 초전자포S 24화 자막(어떤 과학의 초전자포 2기 24화 자막)"}, {"url": "http://fuko.tistory.com/1131", "timestamp": 1379890362, "vendor": "Stankovic", "id": "http://fuko.tistory.com/1131", "title": "10월 신작은 .."}, {"url": "http://r-kai.wo.tc/120198856635", "timestamp": 1380233220, "vendor": "Groove Engine Upbeat TS VIP", "id": "http://r-kai.wo.tc/120198856635", "title": "단간론파 (탄환논파) : 희망의 학원과 절망의 고교생 the Animation 13화 자막 [完]"}, {"url": "http://r-kai.wo.tc/120198549812", "timestamp": 1379799454, "vendor": "Groove Engine Upbeat TS VIP", "id": "http://r-kai.wo.tc/120198549812", "title": "2013년 4분기 자막 작업에 대하여."}, {"url": "http://r-kai.wo.tc/120198465060", "timestamp": 1379648970, "vendor": "Groove Engine Upbeat TS VIP", "id": "http://r-kai.wo.tc/120198465060", "title": "단간론파 (탄환논파) : 희망의 학원과 절망의 고교생 the Animation 12화 자막"}, {"url": "http://r-kai.wo.tc/120198077846", "timestamp": 1379004679, "vendor": "Groove Engine Upbeat TS VIP", "id": "http://r-kai.wo.tc/120198077846", "title": "단간론파 (탄환논파) : 희망의 학원과 절망의 고교생 the Animation 11화 자막"}, {"url": "http://r-kai.wo.tc/120197724875", "timestamp": 1378507425, "vendor": "Groove Engine Upbeat TS VIP", "id": "http://r-kai.wo.tc/120197724875", "title": "내 여동생이 이렇게 귀여울 리가 없어. (2기) 16화 자막 [完]"}, {"url": "http://r-kai.wo.tc/120197650781", "timestamp": 1378406121, "vendor": "Groove Engine Upbeat TS VIP", "id": "http://r-kai.wo.tc/120197650781", "title": "단간론파 (탄환논파) : 희망의 학원과 절망의 고교생 the Animation 10화 자막"}, {"url": "http://melody88.tistory.com/560", "timestamp": 1380391670, "vendor": "Melody의 Subtitle Factory", "id": "http://melody88.tistory.com/560", "title": "어떤 과학의 초전자포 S(2기) 19화 자막"}, {"url": "http://melody88.tistory.com/559", "timestamp": 1380387988, "vendor": "Melody의 Subtitle Factory", "id": "http://melody88.tistory.com/559", "title": "2013년 4분기 자막"}, {"url": "http://melody88.tistory.com/558", "timestamp": 1380387539, "vendor": "Melody의 Subtitle Factory", "id": "http://melody88.tistory.com/558", "title": "모노가타리 세컨드 시즌(오토리모노가타리 2화) 13화 자막"}, {"url": "http://melody88.tistory.com/557", "timestamp": 1379807417, "vendor": "Melody의 Subtitle Factory", "id": "http://melody88.tistory.com/557", "title": "모노가타리 세컨드 시즌(오토리모노가타리 1화) 12화 자막"}, {"url": "http://melody88.tistory.com/556", "timestamp": 1379806974, "vendor": "Melody의 Subtitle Factory", "id": "http://melody88.tistory.com/556", "title": "모노가타리 세컨드 시즌(총집편 2) 11화 자막"}, {"url": "http://melody88.tistory.com/555", "timestamp": 1378606685, "vendor": "Melody의 Subtitle Factory", "id": "http://melody88.tistory.com/555", "title": "모노가타리 세컨드 시즌(카부키모노가타리 4화) 10화 자막"}, {"url": "http://melody88.tistory.com/554", "timestamp": 1377999651, "vendor": "Melody의 Subtitle Factory", "id": "http://melody88.tistory.com/554", "title": "모노가타리 세컨드 시즌(카부키모노가타리 3화) 9화 자막"}, {"url": "http://iriona.egloos.com/3050215", "timestamp": 1379645276, "vendor": "『이리온나』: 어머니, 진서연만 잡고 효도할게요", "id": "http://iriona.egloos.com/3050215", "title": "접는다는 사람이 참 뭔가 길다"}, {"url": "http://eupa.egloos.com/1331119", "timestamp": 1380223900, "vendor": "유파의 자막 블로그", "id": "http://eupa.egloos.com/1331119", "title": "서번트x서비스 제13화 자막"}, {"url": "http://eupa.egloos.com/1330326", "timestamp": 1379809008, "vendor": "유파의 자막 블로그", "id": "http://eupa.egloos.com/1330326", "title": "서번트x서비스 제12화 자막"}, {"url": "http://eupa.egloos.com/1329207", "timestamp": 1379213403, "vendor": "유파의 자막 블로그", "id": "http://eupa.egloos.com/1329207", "title": "서번트x서비스 블루레이 제1권 자막"}, {"url": "http://eupa.egloos.com/1328924", "timestamp": 1379030803, "vendor": "유파의 자막 블로그", "id": "http://eupa.egloos.com/1328924", "title": "서번트x서비스 제11화 자막"}, {"url": "http://eupa.egloos.com/1327908", "timestamp": 1378420669, "vendor": "유파의 자막 블로그", "id": "http://eupa.egloos.com/1327908", "title": "서번트x서비스 제10화 자막"}, {"url": "http://blog.naver.com/baby1255/40198054420", "timestamp": 1380542950, "vendor": "파Oi의 제멋대로 자막 공방 ♬♪", "id": "http://blog.naver.com/baby1255/40198054420", "title": "디아볼릭 러버즈 3 화 자막"}, {"url": "http://blog.naver.com/baby1255/40197759219", "timestamp": 1380110617, "vendor": "파Oi의 제멋대로 자막 공방 ♬♪", "id": "http://blog.naver.com/baby1255/40197759219", "title": "Free! 12 화 자막 (전체 통합본 자막 첨부)"}, {"url": "http://blog.naver.com/baby1255/40197630949", "timestamp": 1379936850, "vendor": "파Oi의 제멋대로 자막 공방 ♬♪", "id": "http://blog.naver.com/baby1255/40197630949", "title": "디아볼릭 러버즈 2 화 자막"}, {"url": "http://blog.naver.com/baby1255/40197415159", "timestamp": 1379588026, "vendor": "파Oi의 제멋대로 자막 공방 ♬♪", "id": "http://blog.naver.com/baby1255/40197415159", "title": "디아볼릭 러버스 1 화 자막"}, {"url": "http://blog.naver.com/baby1255/40197405166", "timestamp": 1379563228, "vendor": "파Oi의 제멋대로 자막 공방 ♬♪", "id": "http://blog.naver.com/baby1255/40197405166", "title": "[공지] 2013년 4분기 애니 자막 예정작"}, {"url": "http://blog.naver.com/colortnk/130176985214", "timestamp": 1380418369, "vendor": "시로유키♡의 하얗고 차가운 결정체를 만드는 블로그", "id": "http://blog.naver.com/colortnk/130176985214", "title": "리코더와 란도셀 3기 자막을 못했네요"}, {"url": "http://jingatter.egloos.com/4829786", "timestamp": 1379839442, "vendor": "THE QOO/대략뒷북 블로킹ヾ(ﾟ口ﾟ@)ヾ(ﾟ口ﾟ@)", "id": "http://jingatter.egloos.com/4829786", "title": "엘리시움: 돈을 재물로 완전 치료를 소환!"}, {"url": "http://jingatter.egloos.com/4829504", "timestamp": 1379712668, "vendor": "THE QOO/대략뒷북 블로킹ヾ(ﾟ口ﾟ@)ヾ(ﾟ口ﾟ@)", "id": "http://jingatter.egloos.com/4829504", "title": "다시 일본으로"}, {"url": "http://jingatter.egloos.com/4827992", "timestamp": 1378974351, "vendor": "THE QOO/대략뒷북 블로킹ヾ(ﾟ口ﾟ@)ヾ(ﾟ口ﾟ@)", "id": "http://jingatter.egloos.com/4827992", "title": "휴가다"}, {"url": "http://jingatter.egloos.com/4825682", "timestamp": 1378012209, "vendor": "THE QOO/대략뒷북 블로킹ヾ(ﾟ口ﾟ@)ヾ(ﾟ口ﾟ@)", "id": "http://jingatter.egloos.com/4825682", "title": "매노부스틸"}, {"url": "http://lookyharu.tistory.com/424", "timestamp": 1380163242, "vendor": "루키하루의 처절한 봄날 작업소", "id": "http://lookyharu.tistory.com/424", "title": "라스트 엑자일 ~은빛 날개의 팜~ 오프닝 Buddy 가사/번역/음악"}, {"url": "http://lookyharu.tistory.com/423", "timestamp": 1379985897, "vendor": "루키하루의 처절한 봄날 작업소", "id": "http://lookyharu.tistory.com/423", "title": "길티크라운 엔딩 Departures 〜あなたにおくるアイの歌(당신에게 바치는 사랑의 노래) 가사/번역"}, {"url": "http://lookyharu.tistory.com/422", "timestamp": 1378861316, "vendor": "루키하루의 처절한 봄날 작업소", "id": "http://lookyharu.tistory.com/422", "title": "DOG DAYS 2기 오프닝 미즈키 나나(水樹奈々) FEARLESS HEROS (가사번역/음원)"}, {"url": "http://blog.naver.com/lightseller/150176169951", "timestamp": 1379648012, "vendor": "광팔이의 조그마한 스케치북", "id": "http://blog.naver.com/lightseller/150176169951", "title": "칸사이 여행기 7/1"}, {"url": "http://blog.naver.com/lightseller/150176168626", "timestamp": 1379646291, "vendor": "광팔이의 조그마한 스케치북", "id": "http://blog.naver.com/lightseller/150176168626", "title": "칸사이 여행기 6/30 -2-"}, {"url": "http://blog.naver.com/lightseller/150175952688", "timestamp": 1379236802, "vendor": "광팔이의 조그마한 스케치북", "id": "http://blog.naver.com/lightseller/150175952688", "title": "child's garden 초벌번역"}, {"url": "http://sukisyo.egloos.com/5773050", "timestamp": 1380400541, "vendor": "미스X의 자막 아지트.", "id": "http://sukisyo.egloos.com/5773050", "title": "카드파이트 뱅가드 링크 죠커 편142화 자막"}, {"url": "http://sukisyo.egloos.com/5771713", "timestamp": 1379867745, "vendor": "미스X의 자막 아지트.", "id": "http://sukisyo.egloos.com/5771713", "title": "카드파이트 뱅가드 링크 죠커 편141화 자막"}, {"url": "http://sukisyo.egloos.com/5770612", "timestamp": 1379353589, "vendor": "미스X의 자막 아지트.", "id": "http://sukisyo.egloos.com/5770612", "title": "카드파이트 뱅가드 링크 죠커 편140화 자막"}, {"url": "http://sukisyo.egloos.com/5768740", "timestamp": 1378597400, "vendor": "미스X의 자막 아지트.", "id": "http://sukisyo.egloos.com/5768740", "title": "카드파이트 뱅가드 링크 죠커 편139화 자막"}, {"url": "http://sukisyo.egloos.com/5767391", "timestamp": 1377983205, "vendor": "미스X의 자막 아지트.", "id": "http://sukisyo.egloos.com/5767391", "title": "카드파이트 뱅가드 링크 죠커 편138화 자막"}, {"url": "http://ssheoos.tistory.com/591", "timestamp": 1380216565, "vendor": "진다의 자막 공방", "id": "http://ssheoos.tistory.com/591", "title": "로젠메이든 신 시리즈 13화 자막 (完)"}, {"url": "http://ssheoos.tistory.com/590", "timestamp": 1379663536, "vendor": "진다의 자막 공방", "id": "http://ssheoos.tistory.com/590", "title": "로젠메이든 신 시리즈 12화 자막"}, {"url": "http://ssheoos.tistory.com/589", "timestamp": 1379036512, "vendor": "진다의 자막 공방", "id": "http://ssheoos.tistory.com/589", "title": "로젠메이든 신 시리즈 11화 자막"}, {"url": "http://ssheoos.tistory.com/588", "timestamp": 1378390602, "vendor": "진다의 자막 공방", "id": "http://ssheoos.tistory.com/588", "title": "로젠메이든 신 시리즈 10화 자막"}, {"url": "http://ssheoos.tistory.com/587", "timestamp": 1378347538, "vendor": "진다의 자막 공방", "id": "http://ssheoos.tistory.com/587", "title": "청의 엑소시스트 Vol.9~10 영상특전 おまけアニメ 裏エク"}, {"url": "http://blog.naver.com/diskql/20195134661", "timestamp": 1378278190, "vendor": "페가서스 섬광권", "id": "http://blog.naver.com/diskql/20195134661", "title": "오오오 나의 애마여~ 알톤 RCT1.0"}, {"url": "http://blog.naver.com/diskql/20195134436", "timestamp": 1378277798, "vendor": "페가서스 섬광권", "id": "http://blog.naver.com/diskql/20195134436", "title": "세인트 세이야 오메가 70화 자막"}, {"url": "http://reisis1464.blog.me/10177096346", "timestamp": 1380401055, "vendor": "레이시스의 자막 쓰레기통", "id": "http://reisis1464.blog.me/10177096346", "title": "헌터x헌터 리메이크 98화 자막"}, {"url": "http://reisis1464.blog.me/10176908445", "timestamp": 1380090137, "vendor": "레이시스의 자막 쓰레기통", "id": "http://reisis1464.blog.me/10176908445", "title": "UN-GO 6화 자막"}, {"url": "http://reisis1464.blog.me/10176721766", "timestamp": 1379824254, "vendor": "레이시스의 자막 쓰레기통", "id": "http://reisis1464.blog.me/10176721766", "title": "헌터x헌터 리메이크 97화 자막"}, {"url": "http://reisis1464.blog.me/10176628309", "timestamp": 1379667098, "vendor": "레이시스의 자막 쓰레기통", "id": "http://reisis1464.blog.me/10176628309", "title": "UN-GO 5화 자막"}, {"url": "http://reisis1464.blog.me/10176569701", "timestamp": 1379549960, "vendor": "레이시스의 자막 쓰레기통", "id": "http://reisis1464.blog.me/10176569701", "title": "개와 가위는 쓰기 나름 12화 자막 (1화~12화)"}, {"url": "http://reisis1464.blog.me/10176377819", "timestamp": 1379216620, "vendor": "레이시스의 자막 쓰레기통", "id": "http://reisis1464.blog.me/10176377819", "title": "헌터x헌터 리메이크 96화 자막"}, {"url": "http://reisis1464.blog.me/10176088784", "timestamp": 1378794417, "vendor": "레이시스의 자막 쓰레기통", "id": "http://reisis1464.blog.me/10176088784", "title": "개와 가위는 쓰기 나름 11화 자막"}, {"url": "http://reisis1464.blog.me/10175942799", "timestamp": 1378605815, "vendor": "레이시스의 자막 쓰레기통", "id": "http://reisis1464.blog.me/10175942799", "title": "헌터x헌터 리메이크 95화 자막"}, {"url": "http://reisis1464.blog.me/10175661981", "timestamp": 1378187192, "vendor": "레이시스의 자막 쓰레기통", "id": "http://reisis1464.blog.me/10175661981", "title": "개와 가위는 쓰기 나름 10화 자막"}, {"url": "http://reisis1464.blog.me/10175505301", "timestamp": 1377985630, "vendor": "레이시스의 자막 쓰레기통", "id": "http://reisis1464.blog.me/10175505301", "title": "헌터x헌터 리메이크 94화 자막"}, {"url": "http://hoki77.blog.me/50179800720", "timestamp": 1379685560, "vendor": "Rolling Rainbow Star_★", "id": "http://hoki77.blog.me/50179800720", "title": "[도쿄 스탑오버] DAY1 : 시나가와 프린스 호텔 / 신주쿠 돈키호테"}, {"url": "http://hoki77.blog.me/50179127232", "timestamp": 1378644183, "vendor": "Rolling Rainbow Star_★", "id": "http://hoki77.blog.me/50179127232", "title": "[도쿄 스탑오버] DAY1 : 지브리미술관 / 키치죠지 마메조, 빌리지 뱅가드 다이너"}, {"url": "http://guqr8311735.tistory.com/entry/dfjerhj346u54u745", "timestamp": 1380499404, "vendor": "크로미트 자막 저장 블로그", "id": "http://guqr8311735.tistory.com/222", "title": "푸른별의 가르강티아 14화 자막 제작 중단합니다."}, {"url": "http://guqr8311735.tistory.com/entry/CROWDS12", "timestamp": 1380343944, "vendor": "크로미트 자막 저장 블로그", "id": "http://guqr8311735.tistory.com/221", "title": "갓챠맨 크라우즈 12화"}, {"url": "http://guqr8311735.tistory.com/entry/CROWDS11", "timestamp": 1379708552, "vendor": "크로미트 자막 저장 블로그", "id": "http://guqr8311735.tistory.com/219", "title": "갓챠맨 크라우즈 11화"}, {"url": "http://guqr8311735.tistory.com/entry/CROWDS10", "timestamp": 1379096852, "vendor": "크로미트 자막 저장 블로그", "id": "http://guqr8311735.tistory.com/218", "title": "갓챠맨 크라우즈 10화"}, {"url": "http://guqr8311735.tistory.com/entry/CROWDS09", "timestamp": 1378498771, "vendor": "크로미트 자막 저장 블로그", "id": "http://guqr8311735.tistory.com/217", "title": "갓챠맨 크라우즈 09화"}, {"url": "http://blog.naver.com/dlalswl40/140196821689", "timestamp": 1378603366, "vendor": "siso x siso", "id": "http://blog.naver.com/dlalswl40/140196821689", "title": "[번역/가사/다운] IA - M'AIDER 조난 Girl「M'AIDER遭難ガール」"}, {"url": "http://blog.naver.com/dlalswl40/140196817525", "timestamp": 1378598308, "vendor": "siso x siso", "id": "http://blog.naver.com/dlalswl40/140196817525", "title": "[번역/가사/다운] GUMI - 세계수명과 마지막 하루「世界寿命と最後の一日」"}, {"url": "http://blog.naver.com/dlalswl40/140196814531", "timestamp": 1378594771, "vendor": "siso x siso", "id": "http://blog.naver.com/dlalswl40/140196814531", "title": "[번역/가사/다운] GUMI - 나는 분위기를 읽지 못한다「僕は空気が嫁ない」"}, {"url": "http://blog.naver.com/dlalswl40/140196477437", "timestamp": 1378105786, "vendor": "siso x siso", "id": "http://blog.naver.com/dlalswl40/140196477437", "title": "[번역/가사/다운] IA - 서머타임 레코드「サマータイムレコード」"}, {"url": "http://blog.naver.com/dlalswl40/140196382390", "timestamp": 1377991680, "vendor": "siso x siso", "id": "http://blog.naver.com/dlalswl40/140196382390", "title": "[번역/가사/다운] 카가미네 린 - 세상에서 제일 아름다운 아침에「世界で一番きれいな朝に」"}, {"url": "http://blog.naver.com/dlalswl40/140196379655", "timestamp": 1377988933, "vendor": "siso x siso", "id": "http://blog.naver.com/dlalswl40/140196379655", "title": "[번역/가사/다운] 카가미네 렌 - 성창폭렬 Boy「聖槍爆裂ボーイ」"}, {"url": "http://spinel.egloos.com/5202799", "timestamp": 1379211412, "vendor": "스피넬의 라온새", "id": "http://spinel.egloos.com/5202799", "title": "슈퍼 청춘 브라더스 1화 자막"}, {"url": "http://blog.naver.com/already95/10176633531", "timestamp": 1379693073, "vendor": ".", "id": "http://blog.naver.com/already95/10176633531", "title": "9월 하반기 시즌 중간 집계"}, {"url": "http://blog.naver.com/already95/10175819198", "timestamp": 1378418962, "vendor": ".", "id": "http://blog.naver.com/already95/10175819198", "title": "9월 상반기 시즌 중간 집계"}, {"url": "http://ganari20.blog.me/100196885329", "timestamp": 1380390139, "vendor": "가나리의 블로그", "id": "http://ganari20.blog.me/100196885329", "title": "모노가타리 시리즈 세컨드 시즌 13화 자막"}, {"url": "http://ganari20.blog.me/100196827254", "timestamp": 1380297430, "vendor": "가나리의 블로그", "id": "http://ganari20.blog.me/100196827254", "title": "공의 경계 13화 자막 (終)"}, {"url": "http://ganari20.blog.me/100196504782", "timestamp": 1379835503, "vendor": "가나리의 블로그", "id": "http://ganari20.blog.me/100196504782", "title": "공의 경계 12화 자막"}, {"url": "http://ganari20.blog.me/100196456581", "timestamp": 1379777493, "vendor": "가나리의 블로그", "id": "http://ganari20.blog.me/100196456581", "title": "모노가타리 시리즈 세컨드 시즌 12화 자막"}, {"url": "http://ganari20.blog.me/100196059696", "timestamp": 1379102158, "vendor": "가나리의 블로그", "id": "http://ganari20.blog.me/100196059696", "title": "공의 경계 11화 자막"}, {"url": "http://ganari20.blog.me/100195690747", "timestamp": 1378599530, "vendor": "가나리의 블로그", "id": "http://ganari20.blog.me/100195690747", "title": "공의 경계 10화 자막"}, {"url": "http://ganari20.blog.me/100195671942", "timestamp": 1378576580, "vendor": "가나리의 블로그", "id": "http://ganari20.blog.me/100195671942", "title": "Fate/kaleid liner 프리즈마☆이리야 10화 자막 (終)"}, {"url": "http://ganari20.blog.me/100195237285", "timestamp": 1377981190, "vendor": "가나리의 블로그", "id": "http://ganari20.blog.me/100195237285", "title": "공의 경계 9화 자막"}, {"url": "http://ganari20.blog.me/100195224490", "timestamp": 1377961299, "vendor": "가나리의 블로그", "id": "http://ganari20.blog.me/100195224490", "title": "Fate/kaleid liner 프리즈마☆이리야 9화 자막"}, {"url": "http://ll_orz.blog.me/70176396667", "timestamp": 1380289560, "vendor": "스피넬의 라온새", "id": "http://ll_orz.blog.me/70176396667", "title": "슈퍼 청춘 브라더스 3화 자막"}, {"url": "http://ll_orz.blog.me/70176147737", "timestamp": 1379919783, "vendor": "스피넬의 라온새", "id": "http://ll_orz.blog.me/70176147737", "title": "치하야후루2 26화 (OAD) 자막"}, {"url": "http://ll_orz.blog.me/70175985976", "timestamp": 1379681016, "vendor": "스피넬의 라온새", "id": "http://ll_orz.blog.me/70175985976", "title": "슈퍼 청춘 브라더스 1~2화 자막"}, {"url": "http://ll_orz.blog.me/70175625412", "timestamp": 1379044444, "vendor": "스피넬의 라온새", "id": "http://ll_orz.blog.me/70175625412", "title": "2013년 4분기 자막 작업 작품"}, {"url": "http://blog.naver.com/roefore12/110176850462", "timestamp": 1380404730, "vendor": "NEWFUTURE의 アニメ 자막연구소", "id": "http://blog.naver.com/roefore12/110176850462", "title": "헌터x헌터 리메이크 98화자막"}, {"url": "http://blog.naver.com/roefore12/110176782067", "timestamp": 1380291504, "vendor": "NEWFUTURE의 アニメ 자막연구소", "id": "http://blog.naver.com/roefore12/110176782067", "title": "스텔라 여학원 고등과 C3부 13화 자막(수정본)"}, {"url": "http://blog.naver.com/roefore12/110176752263", "timestamp": 1380239652, "vendor": "NEWFUTURE의 アニメ 자막연구소", "id": "http://blog.naver.com/roefore12/110176752263", "title": "아....... 진심 ㅡㅡ"}, {"url": "http://blog.naver.com/roefore12/110176607120", "timestamp": 1380029186, "vendor": "NEWFUTURE의 アニメ 자막연구소", "id": "http://blog.naver.com/roefore12/110176607120", "title": "시험이라니....."}, {"url": "http://blog.naver.com/roefore12/110176467156", "timestamp": 1379822533, "vendor": "NEWFUTURE의 アニメ 자막연구소", "id": "http://blog.naver.com/roefore12/110176467156", "title": "님들 4분기 애니중에.. 겁쟁이 페달하고 벚꽃사중주"}, {"url": "http://blog.naver.com/roefore12/110176466894", "timestamp": 1379822338, "vendor": "NEWFUTURE의 アニメ 자막연구소", "id": "http://blog.naver.com/roefore12/110176466894", "title": "우리를 덕후로,사람들을 어둠의세계로 빠뜨렸던 애니들"}, {"url": "http://blog.naver.com/roefore12/110176447966", "timestamp": 1379802211, "vendor": "NEWFUTURE의 アニメ 자막연구소", "id": "http://blog.naver.com/roefore12/110176447966", "title": "헌터x헌터 리메이크 97화 자막"}, {"url": "http://blog.naver.com/roefore12/110176434502", "timestamp": 1379785505, "vendor": "NEWFUTURE의 アニメ 자막연구소", "id": "http://blog.naver.com/roefore12/110176434502", "title": "환영을 달리는 태양 12화 자막"}, {"url": "http://blog.naver.com/roefore12/110176429568", "timestamp": 1379773665, "vendor": "NEWFUTURE의 アニメ 자막연구소", "id": "http://blog.naver.com/roefore12/110176429568", "title": "오 지리네요 슈퍼 소니코 애니화라니 ㅋㅋㅋ"}, {"url": "http://blog.naver.com/roefore12/110176399198", "timestamp": 1379722347, "vendor": "NEWFUTURE의 アニメ 자막연구소", "id": "http://blog.naver.com/roefore12/110176399198", "title": "두 사람은 밀키홈즈 10화 자막"}, {"url": "http://blog.naver.com/roefore12/110176329296", "timestamp": 1379588617, "vendor": "NEWFUTURE의 アニメ 자막연구소", "id": "http://blog.naver.com/roefore12/110176329296", "title": "스텔라 여학원 고등과 C3부 12화 자막"}, {"url": "http://blog.naver.com/roefore12/110176292727", "timestamp": 1379494700, "vendor": "NEWFUTURE의 アニメ 자막연구소", "id": "http://blog.naver.com/roefore12/110176292727", "title": "아 잠이 안오네요.. 드디어 자막제작 시작하려 합니다."}, {"url": "http://blog.naver.com/roefore12/110176021057", "timestamp": 1379049777, "vendor": "NEWFUTURE의 アニメ 자막연구소", "id": "http://blog.naver.com/roefore12/110176021057", "title": "스텥라 여학원 고등과 C3부 제11화 자막"}, {"url": "http://blog.naver.com/roefore12/110175889256", "timestamp": 1378866637, "vendor": "NEWFUTURE의 アニメ 자막연구소", "id": "http://blog.naver.com/roefore12/110175889256", "title": "던파시작했음다 ㅋㅋ"}, {"url": "http://blog.naver.com/roefore12/110175693173", "timestamp": 1378599878, "vendor": "NEWFUTURE의 アニメ 자막연구소", "id": "http://blog.naver.com/roefore12/110175693173", "title": "아 블러드래드완결이라닠ㄲㄲ"}, {"url": "http://blog.naver.com/roefore12/110175676018", "timestamp": 1378578513, "vendor": "NEWFUTURE의 アニメ 자막연구소", "id": "http://blog.naver.com/roefore12/110175676018", "title": "ㄷㄷ"}, {"url": "http://blog.naver.com/roefore12/110175652227", "timestamp": 1378527249, "vendor": "NEWFUTURE의 アニメ 자막연구소", "id": "http://blog.naver.com/roefore12/110175652227", "title": "게임하시는분 추천좀?"}, {"url": "http://blog.naver.com/roefore12/110175643135", "timestamp": 1378517356, "vendor": "NEWFUTURE의 アニメ 자막연구소", "id": "http://blog.naver.com/roefore12/110175643135", "title": "10월 4분기자막예정"}, {"url": "http://blog.naver.com/roefore12/110175598212", "timestamp": 1378440308, "vendor": "NEWFUTURE의 アニメ 자막연구소", "id": "http://blog.naver.com/roefore12/110175598212", "title": "스텔라 여학원 고등과 C3부 제10화 자막[레오퍼드추가]"}, {"url": "http://blog.naver.com/roefore12/110175585591", "timestamp": 1378426685, "vendor": "NEWFUTURE의 アニメ 자막연구소", "id": "http://blog.naver.com/roefore12/110175585591", "title": "드디어 학교에서돌아왔다.."}, {"url": "http://blog.naver.com/roefore12/110175351045", "timestamp": 1378096089, "vendor": "NEWFUTURE의 アニメ 자막연구소", "id": "http://blog.naver.com/roefore12/110175351045", "title": "으악 모의고사라니.."}, {"url": "http://apricot.wo.tc/140198074238", "timestamp": 1380488372, "vendor": "Rolling! Rolling!", "id": "http://apricot.wo.tc/140198074238", "title": "로큐브에서 찾아낸 미스터리."}, {"url": "http://blog.naver.com/juchasin/80198804366", "timestamp": 1380282061, "vendor": "주차신의 번역창고", "id": "http://blog.naver.com/juchasin/80198804366", "title": "'아웃브레이크 컴퍼니' 자막 시작하겠습니다."}, {"url": "http://blog.naver.com/juchasin/80198656424", "timestamp": 1380065409, "vendor": "주차신의 번역창고", "id": "http://blog.naver.com/juchasin/80198656424", "title": "일상 자막 (BD용 자막, 0화~26화)"}, {"url": "http://blog.naver.com/juchasin/80198620134", "timestamp": 1380006505, "vendor": "주차신의 번역창고", "id": "http://blog.naver.com/juchasin/80198620134", "title": "블로그 이전하였습니다."}, {"url": "http://blog.naver.com/3hope3/70176449797", "timestamp": 1380368122, "vendor": "고양이집", "id": "http://blog.naver.com/3hope3/70176449797", "title": "[BD] デート・ア・ライブ 데이트 어 라이브 Vol.4 블루레이 자막"}, {"url": "http://blog.naver.com/3hope3/70176449281", "timestamp": 1380364458, "vendor": "고양이집", "id": "http://blog.naver.com/3hope3/70176449281", "title": "超次元ゲイム ネプテューヌ 초차원게임 넵튠 12화 자막"}, {"url": "http://blog.naver.com/3hope3/70176396255", "timestamp": 1380286922, "vendor": "고양이집", "id": "http://blog.naver.com/3hope3/70176396255", "title": "戦姫絶唱シンフォギアＧ 전희절창 심포기어 G 13화 자막 (完)"}, {"url": "http://blog.naver.com/3hope3/70176396125", "timestamp": 1380286085, "vendor": "고양이집", "id": "http://blog.naver.com/3hope3/70176396125", "title": "용어해설 - 34. 신수경"}, {"url": "http://blog.naver.com/3hope3/70176373903", "timestamp": 1380245704, "vendor": "고양이집", "id": "http://blog.naver.com/3hope3/70176373903", "title": "용어해설 - 33. LiNKER"}, {"url": "http://blog.naver.com/3hope3/70176373805", "timestamp": 1380245589, "vendor": "고양이집", "id": "http://blog.naver.com/3hope3/70176373805", "title": "용어해설 - 32. F.I.S."}, {"url": "http://blog.naver.com/3hope3/70176373294", "timestamp": 1380244972, "vendor": "고양이집", "id": "http://blog.naver.com/3hope3/70176373294", "title": "용어해설 - 31. 오가와 일족"}, {"url": "http://blog.naver.com/3hope3/70176373197", "timestamp": 1380244890, "vendor": "고양이집", "id": "http://blog.naver.com/3hope3/70176373197", "title": "용어해설 - 30. 2과 가설 본부"}, {"url": "http://blog.naver.com/3hope3/70176373131", "timestamp": 1380244821, "vendor": "고양이집", "id": "http://blog.naver.com/3hope3/70176373131", "title": "용어해설 - 29. 사립 리디안 음악원"}, {"url": "http://blog.naver.com/3hope3/70176373061", "timestamp": 1380244749, "vendor": "고양이집", "id": "http://blog.naver.com/3hope3/70176373061", "title": "용어해설 - 28. 수수께끼의 가스"}, {"url": "http://blog.naver.com/3hope3/70176372976", "timestamp": 1380244647, "vendor": "고양이집", "id": "http://blog.naver.com/3hope3/70176372976", "title": "용어해설 - 27. 네피림"}, {"url": "http://blog.naver.com/3hope3/70176372890", "timestamp": 1380244553, "vendor": "고양이집", "id": "http://blog.naver.com/3hope3/70176372890", "title": "용어 해설 - 26. 하마자키 병원"}, {"url": "http://blog.naver.com/3hope3/70176372799", "timestamp": 1380244441, "vendor": "고양이집", "id": "http://blog.naver.com/3hope3/70176372799", "title": "용어해설 - 25. S 2 C A"}, {"url": "http://blog.naver.com/3hope3/70176372700", "timestamp": 1380244325, "vendor": "고양이집", "id": "http://blog.naver.com/3hope3/70176372700", "title": "용어해설 - 24. 절창"}, {"url": "http://blog.naver.com/3hope3/70176338168", "timestamp": 1380198968, "vendor": "고양이집", "id": "http://blog.naver.com/3hope3/70176338168", "title": "용어설명 - 23. 암드기어"}, {"url": "http://blog.naver.com/3hope3/70176338155", "timestamp": 1380198905, "vendor": "고양이집", "id": "http://blog.naver.com/3hope3/70176338155", "title": "용어해설 - 22. 이갈리마"}, {"url": "http://blog.naver.com/3hope3/70176338146", "timestamp": 1380198848, "vendor": "고양이집", "id": "http://blog.naver.com/3hope3/70176338146", "title": "용어해설 - 21. 슐 샤가나"}, {"url": "http://blog.naver.com/3hope3/70176338086", "timestamp": 1380198300, "vendor": "고양이집", "id": "http://blog.naver.com/3hope3/70176338086", "title": "용어해설 - 20. 검은 건그닐"}, {"url": "http://blog.naver.com/3hope3/70176338039", "timestamp": 1380197934, "vendor": "고양이집", "id": "http://blog.naver.com/3hope3/70176338039", "title": "용어해설 - 19. 루루・아메루와 카스토디안(보관자)"}, {"url": "http://blog.naver.com/3hope3/70176337909", "timestamp": 1380197427, "vendor": "고양이집", "id": "http://blog.naver.com/3hope3/70176337909", "title": "용어해설 - 18. 달"}, {"url": "http://blog.naver.com/3hope3/70176337686", "timestamp": 1380195853, "vendor": "고양이집", "id": "http://blog.naver.com/3hope3/70176337686", "title": "용어해설 - 17. 솔로몬의 지팡이"}, {"url": "http://blog.naver.com/3hope3/70176337629", "timestamp": 1380195365, "vendor": "고양이집", "id": "http://blog.naver.com/3hope3/70176337629", "title": "용어해설 - 16. 수수께끼의 무장조직"}, {"url": "http://blog.naver.com/3hope3/70176337564", "timestamp": 1380194866, "vendor": "고양이집", "id": "http://blog.naver.com/3hope3/70176337564", "title": "용어해설 - 15. 피네"}, {"url": "http://blog.naver.com/3hope3/70176337503", "timestamp": 1380194279, "vendor": "고양이집", "id": "http://blog.naver.com/3hope3/70176337503", "title": "용어해설 - 14. 현재의 세계정세"}, {"url": "http://blog.naver.com/3hope3/70176337304", "timestamp": 1380192202, "vendor": "고양이집", "id": "http://blog.naver.com/3hope3/70176337304", "title": "용어해설 - 13. 특이 재해 대책 기동부"}, {"url": "http://blog.naver.com/3hope3/70176337293", "timestamp": 1380192105, "vendor": "고양이집", "id": "http://blog.naver.com/3hope3/70176337293", "title": "용어해설 - 12. 건그닐"}, {"url": "http://blog.naver.com/3hope3/70176337281", "timestamp": 1380191983, "vendor": "고양이집", "id": "http://blog.naver.com/3hope3/70176337281", "title": "용어해설 - 11. 이치이발"}, {"url": "http://blog.naver.com/3hope3/70176337277", "timestamp": 1380191935, "vendor": "고양이집", "id": "http://blog.naver.com/3hope3/70176337277", "title": "용어해설 - 10. 아메노 하바키리"}, {"url": "http://blog.naver.com/3hope3/70176337274", "timestamp": 1380191881, "vendor": "고양이집", "id": "http://blog.naver.com/3hope3/70176337274", "title": "용어해설 - 9. 적합자"}, {"url": "http://blog.naver.com/3hope3/70176337254", "timestamp": 1380191669, "vendor": "고양이집", "id": "http://blog.naver.com/3hope3/70176337254", "title": "용어해설 - 8. 주자(装者)의 팬던트"}, {"url": "http://blog.naver.com/3hope3/70176337236", "timestamp": 1380191529, "vendor": "고양이집", "id": "http://blog.naver.com/3hope3/70176337236", "title": "용어해설 - 7. 성유물"}, {"url": "http://blog.naver.com/3hope3/70176337207", "timestamp": 1380191337, "vendor": "고양이집", "id": "http://blog.naver.com/3hope3/70176337207", "title": "용어해설 - 6. 루나 어택"}, {"url": "http://blog.naver.com/3hope3/70176337190", "timestamp": 1380191243, "vendor": "고양이집", "id": "http://blog.naver.com/3hope3/70176337190", "title": "용어해설 - 5. 라이브 회장의 참극"}, {"url": "http://blog.naver.com/wdrop14/60200726063", "timestamp": 1380356194, "vendor": "싯쭈 - WATERDROP", "id": "http://blog.naver.com/wdrop14/60200726063", "title": "단간론파(ダンガンロンパ) THE ANIMATION 1~13화 자막 모음"}, {"url": "http://blog.naver.com/wdrop14/60200725251", "timestamp": 1380354568, "vendor": "싯쭈 - WATERDROP", "id": "http://blog.naver.com/wdrop14/60200725251", "title": "단간론파(ダンガンロンパ) THE ANIMATION 13화 자막(完)"}, {"url": "http://blog.naver.com/wdrop14/60200541965", "timestamp": 1380078684, "vendor": "싯쭈 - WATERDROP", "id": "http://blog.naver.com/wdrop14/60200541965", "title": "4분기 자막제작은"}, {"url": "http://blog.naver.com/wdrop14/60200233036", "timestamp": 1379609502, "vendor": "싯쭈 - WATERDROP", "id": "http://blog.naver.com/wdrop14/60200233036", "title": "단간론파(ダンガンロンパ) THE ANIMATION 12화 자막"}, {"url": "http://blog.naver.com/wdrop14/60200207109", "timestamp": 1379542899, "vendor": "싯쭈 - WATERDROP", "id": "http://blog.naver.com/wdrop14/60200207109", "title": "쓰르라미 울 적에 확(拡) 아웃브레이크 자막"}, {"url": "http://blog.naver.com/wdrop14/60200004185", "timestamp": 1379197667, "vendor": "싯쭈 - WATERDROP", "id": "http://blog.naver.com/wdrop14/60200004185", "title": "단간론파(ダンガンロンパ) THE ANIMATION 11화 자막"}, {"url": "http://blog.naver.com/wdrop14/60199730957", "timestamp": 1378791588, "vendor": "싯쭈 - WATERDROP", "id": "http://blog.naver.com/wdrop14/60199730957", "title": "단간론파 자막 수정 관련"}, {"url": "http://blog.naver.com/wdrop14/60199487168", "timestamp": 1378436347, "vendor": "싯쭈 - WATERDROP", "id": "http://blog.naver.com/wdrop14/60199487168", "title": "단간론파(ダンガンロンパ) THE ANIMATION 10화 자막"}, {"url": "http://apricot.wo.tc/140197103354", "timestamp": 1378966909, "vendor": "Rolling! Rolling!", "id": "http://apricot.wo.tc/140197103354", "title": "暁切歌 (CV.茅野愛衣) - 手紙"}, {"url": "http://apricot.wo.tc/140197103346", "timestamp": 1378966903, "vendor": "Rolling! Rolling!", "id": "http://apricot.wo.tc/140197103346", "title": "暁切歌 (CV.茅野愛衣) - 獄鎌・イガリマ"}, {"url": "http://apricot.wo.tc/140196645122", "timestamp": 1378341669, "vendor": "Rolling! Rolling!", "id": "http://apricot.wo.tc/140196645122", "title": "アフィリア・サーガ - ネプテューヌ☆サガして"}, {"url": "http://apricot.wo.tc/140196642417", "timestamp": 1378339204, "vendor": "Rolling! Rolling!", "id": "http://apricot.wo.tc/140196642417", "title": "雪音クリス (CV. 高垣彩陽) - 教室モノクローム"}, {"url": "http://apricot.wo.tc/140196638380", "timestamp": 1378335687, "vendor": "Rolling! Rolling!", "id": "http://apricot.wo.tc/140196638380", "title": "雪音クリス (CV. 高垣彩陽) - Bye-Bye Lullaby"}, {"url": "http://apricot.wo.tc/140196626812", "timestamp": 1378325077, "vendor": "Rolling! Rolling!", "id": "http://apricot.wo.tc/140196626812", "title": "月読調 (CV. 南條愛乃) - PRACTICE MODE"}, {"url": "http://apricot.wo.tc/140196626804", "timestamp": 1378325063, "vendor": "Rolling! Rolling!", "id": "http://apricot.wo.tc/140196626804", "title": "月読調 (CV. 南條愛乃) - 鏖鋸・シュルシャガナ"}, {"url": "http://apricot.wo.tc/140196626471", "timestamp": 1378324745, "vendor": "Rolling! Rolling!", "id": "http://apricot.wo.tc/140196626471", "title": "風鳴翼 (CV. 水樹奈々) - 恋の桶狭間"}, {"url": "http://apricot.wo.tc/140196626465", "timestamp": 1378324743, "vendor": "Rolling! Rolling!", "id": "http://apricot.wo.tc/140196626465", "title": "風鳴翼 (CV. 水樹奈々) - 月煌ノ剣"}, {"url": "http://apricot.wo.tc/140196527403", "timestamp": 1378178001, "vendor": "Rolling! Rolling!", "id": "http://apricot.wo.tc/140196527403", "title": "マリア・カデンツァヴナ・イヴ (CV. 日笠陽子) - Dark Oblivion"}, {"url": "http://apricot.wo.tc/140196527400", "timestamp": 1378177997, "vendor": "Rolling! Rolling!", "id": "http://apricot.wo.tc/140196527400", "title": "マリア・カデンツァヴナ・イヴ (CV. 日笠陽子) - 烈槍・ガングニール"}, {"url": "http://apricot.wo.tc/140196527397", "timestamp": 1378177994, "vendor": "Rolling! Rolling!", "id": "http://apricot.wo.tc/140196527397", "title": "立花響 (CV. 悠木碧) - Rainbow Flower"}, {"url": "http://apricot.wo.tc/140196527386", "timestamp": 1378177987, "vendor": "Rolling! Rolling!", "id": "http://apricot.wo.tc/140196527386", "title": "立花響 (CV. 悠木碧) - 正義を信じて、握り締めて"}, {"url": "http://apricot.wo.tc/140196527383", "timestamp": 1378177982, "vendor": "Rolling! Rolling!", "id": "http://apricot.wo.tc/140196527383", "title": "マリア・カデンツァヴナ・イヴ (CV. 日笠陽子), 風鳴翼 (CV .水樹奈々) - 不死鳥のフランメ"}, {"url": "http://apricot.wo.tc/140196522886", "timestamp": 1378174152, "vendor": "Rolling! Rolling!", "id": "http://apricot.wo.tc/140196522886", "title": "高垣彩陽 - Next Destination"}, {"url": "http://apricot.wo.tc/140196521525", "timestamp": 1378172942, "vendor": "Rolling! Rolling!", "id": "http://apricot.wo.tc/140196521525", "title": "水樹奈々 - Vitalization"}, {"url": "http://apricot.wo.tc/140196519856", "timestamp": 1378171191, "vendor": "Rolling! Rolling!", "id": "http://apricot.wo.tc/140196519856", "title": "立花響 (CV. 悠木碧), 風鳴翼 (CV. 水樹奈々), 雪音クリス (CV. 高垣彩陽) - FIRST LOVE SONG"}, {"url": "http://apricot.wo.tc/140196519812", "timestamp": 1378171134, "vendor": "Rolling! Rolling!", "id": "http://apricot.wo.tc/140196519812", "title": "小日向未来 (CV. 井口裕香) - 陽だまりメモリア"}, {"url": "http://apricot.wo.tc/140196461122", "timestamp": 1378090914, "vendor": "Rolling! Rolling!", "id": "http://apricot.wo.tc/140196461122", "title": "天羽奏 (CV. 高山みなみ) - 君ト云ウ音奏デ尽キルマデ"}, {"url": "http://apricot.wo.tc/140196448210", "timestamp": 1378078934, "vendor": "Rolling! Rolling!", "id": "http://apricot.wo.tc/140196448210", "title": "雪音クリス (CV. 高垣彩陽) - 繋いだ手だけが紡ぐもの"}, {"url": "http://apricot.wo.tc/140196448204", "timestamp": 1378078927, "vendor": "Rolling! Rolling!", "id": "http://apricot.wo.tc/140196448204", "title": "雪音クリス (CV. 高垣彩陽) - 魔弓・イチイバル"}, {"url": "http://apricot.wo.tc/140196448202", "timestamp": 1378078923, "vendor": "Rolling! Rolling!", "id": "http://apricot.wo.tc/140196448202", "title": "風鳴翼 (CV. 水樹奈々) - FLIGHT FEATHERS"}, {"url": "http://apricot.wo.tc/140196448195", "timestamp": 1378078918, "vendor": "Rolling! Rolling!", "id": "http://apricot.wo.tc/140196448195", "title": "風鳴翼 (CV. 水樹奈々) - 絶刀・天羽々斬"}, {"url": "http://apricot.wo.tc/140196410531", "timestamp": 1378019229, "vendor": "Rolling! Rolling!", "id": "http://apricot.wo.tc/140196410531", "title": "立花響 (CV. 悠木碧) - 私ト云ウ 音響キ ソノ先ニ"}, {"url": "http://apricot.wo.tc/140196410527", "timestamp": 1378019226, "vendor": "Rolling! Rolling!", "id": "http://apricot.wo.tc/140196410527", "title": "立花響 (CV. 悠木碧) - 撃槍・ガングニール"}, {"url": "http://apricot.wo.tc/140196403158", "timestamp": 1378011812, "vendor": "Rolling! Rolling!", "id": "http://apricot.wo.tc/140196403158", "title": "Zwei Wing - ORBITAL BEAT"}, {"url": "http://apricot.wo.tc/140196403154", "timestamp": 1378011808, "vendor": "Rolling! Rolling!", "id": "http://apricot.wo.tc/140196403154", "title": "Zwei Wing - 逆光のフリューゲル"}, {"url": "http://fuko.tistory.com/1128", "timestamp": 1378409587, "vendor": "???", "id": "http://fuko.tistory.com/1128", "title": "태클 걸 곳이 너무 많은 금서목록 1편"}]}